{"update_time":1619581413639,"date_list":[{"date":"20200101","type":2,"holiday":"元旦"},{"date":"20200119","type":1,"holiday":""},{"date":"20200124","type":2,"holiday":"春节"},{"date":"20200125","type":2,"holiday":"春节"},{"date":"20200126","type":2,"holiday":"春节"},{"date":"20200127","type":2,"holiday":"春节"},{"date":"20200128","type":2,"holiday":"春节"},{"date":"20200129","type":2,"holiday":"春节"},{"date":"20200130","type":2,"holiday":"春节"},{"date":"20200131","type":2,"holiday":"春节"},{"date":"20200201","type":2,"holiday":"春节"},{"date":"20200202","type":2,"holiday":"春节"},{"date":"20200404","type":2,"holiday":"清明"},{"date":"20200405","type":2,"holiday":"清明"},{"date":"20200406","type":2,"holiday":"清明"},{"date":"20200426","type":1,"holiday":""},{"date":"20200501","type":2,"holiday":"五一"},{"date":"20200502","type":2,"holiday":"五一"},{"date":"20200503","type":2,"holiday":"五一"},{"date":"20200504","type":2,"holiday":"五一"},{"date":"20200505","type":2,"holiday":"五一"},{"date":"20200509","type":1,"holiday":""},{"date":"20200625","type":2,"holiday":"端午"},{"date":"20200626","type":2,"holiday":"端午"},{"date":"20200627","type":2,"holiday":"端午"},{"date":"20200628","type":1,"holiday":""},{"date":"20200927","type":1,"holiday":""},{"date":"20201001","type":2,"holiday":"国庆"},{"date":"20201002","type":2,"holiday":"国庆"},{"date":"20201003","type":2,"holiday":"国庆"},{"date":"20201004","type":2,"holiday":"国庆"},{"date":"20201005","type":2,"holiday":"国庆"},{"date":"20201006","type":2,"holiday":"国庆"},{"date":"20201007","type":2,"holiday":"国庆"},{"date":"20201008","type":2,"holiday":"国庆"},{"date":"20201010","type":1,"holiday":""},{"date":"20210101","type":2,"holiday":"元旦"},{"date":"20210102","type":2,"holiday":"元旦"},{"date":"20210103","type":2,"holiday":"元旦"},{"date":"20210207","type":1,"holiday":""},{"date":"20210211","type":2,"holiday":"春节"},{"date":"20210212","type":2,"holiday":"春节"},{"date":"20210213","type":2,"holiday":"春节"},{"date":"20210214","type":2,"holiday":"春节"},{"date":"20210215","type":2,"holiday":"春节"},{"date":"20210216","type":2,"holiday":"春节"},{"date":"20210217","type":2,"holiday":"春节"},{"date":"20210220","type":1,"holiday":""},{"date":"20210403","type":2,"holiday":"清明"},{"date":"20210404","type":2,"holiday":"清明"},{"date":"20210405","type":2,"holiday":"清明"},{"date":"20210425","type":1,"holiday":""},{"date":"20210501","type":2,"holiday":"五一"},{"date":"20210502","type":2,"holiday":"五一"},{"date":"20210503","type":2,"holiday":"五一"},{"date":"20210504","type":2,"holiday":"五一"},{"date":"20210505","type":2,"holiday":"五一"},{"date":"20210508","type":1,"holiday":""},{"date":"20210612","type":2,"holiday":"休"},{"date":"20210613","type":2,"holiday":"休"},{"date":"20210614","type":2,"holiday":"端午节"},{"date":"20210919","type":2,"holiday":"休"},{"date":"20210920","type":2,"holiday":"休"},{"date":"20210921","type":2,"holiday":"中秋节"},{"date":"20211001","type":2,"holiday":"国庆节"},{"date":"20211002","type":2,"holiday":"休"},{"date":"20211003","type":2,"holiday":"休"},{"date":"20211004","type":2,"holiday":"休"},{"date":"20211005","type":2,"holiday":"休"},{"date":"20211006","type":2,"holiday":"休"},{"date":"20211007","type":2,"holiday":"休"},{"date":"20211009","type":1,"holiday":""}]}